{
  "hero": "doom",
  "patch": "7.39E",
  "updated_at": "2025-10-03T15:12:33Z",
  "matchups": [
    {
      "opponent": "abaddon",
      "winrate": 42.7908,
      "disadvantage": -2.1432,
      "matches": 22409
    },
    {
      "opponent": "alchemist",
      "winrate": 44.7558,
      "disadvantage": -1.9259,
      "matches": 21376
    },
    {
      "opponent": "ancient-apparition",
      "winrate": 42.5506,
      "disadvantage": -0.0233,
      "matches": 21955
    },
    {
      "opponent": "anti-mage",
      "winrate": 40.5597,
      "disadvantage": 1.2132,
      "matches": 49739
    },
    {
      "opponent": "arc-warden",
      "winrate": 43.7178,
      "disadvantage": -0.3987,
      "matches": 6805
    },
    {
      "opponent": "axe",
      "winrate": 42.8332,
      "disadvantage": -1.0075,
      "matches": 58618
    },
    {
      "opponent": "bane",
      "winrate": 45.7639,
      "disadvantage": -2.0919,
      "matches": 9372
    },
    {
      "opponent": "batrider",
      "winrate": 47.6418,
      "disadvantage": 0.9677,
      "matches": 5428
    },
    {
      "opponent": "beastmaster",
      "winrate": 49.1445,
      "disadvantage": -0.8701,
      "matches": 13560
    },
    {
      "opponent": "bloodseeker",
      "winrate": 46.5433,
      "disadvantage": -2.1698,
      "matches": 9084
    },
    {
      "opponent": "bounty-hunter",
      "winrate": 45.6753,
      "disadvantage": -1.5599,
      "matches": 13793
    },
    {
      "opponent": "brewmaster",
      "winrate": 48.8931,
      "disadvantage": -4.7372,
      "matches": 4201
    },
    {
      "opponent": "bristleback",
      "winrate": 47.7895,
      "disadvantage": 0.0757,
      "matches": 20584
    },
    {
      "opponent": "broodmother",
      "winrate": 42.5173,
      "disadvantage": -1.3855,
      "matches": 6348
    },
    {
      "opponent": "centaur-warrunner",
      "winrate": 42.9856,
      "disadvantage": -1.0869,
      "matches": 24892
    },
    {
      "opponent": "chaos-knight",
      "winrate": 43.2922,
      "disadvantage": -1.194,
      "matches": 13954
    },
    {
      "opponent": "chen",
      "winrate": 51.5585,
      "disadvantage": -4.4546,
      "matches": 2374
    },
    {
      "opponent": "clinkz",
      "winrate": 40.682,
      "disadvantage": 0.7462,
      "matches": 11231
    },
    {
      "opponent": "clockwerk",
      "winrate": 42.1216,
      "disadvantage": 0.0731,
      "matches": 15073
    },
    {
      "opponent": "crystal-maiden",
      "winrate": 42.8049,
      "disadvantage": 1.3031,
      "matches": 25983
    },
    {
      "opponent": "dark-seer",
      "winrate": 46.9148,
      "disadvantage": -2.4694,
      "matches": 4700
    },
    {
      "opponent": "dark-willow",
      "winrate": 43.8181,
      "disadvantage": 0.7689,
      "matches": 13572
    },
    {
      "opponent": "dawnbreaker",
      "winrate": 42.0821,
      "disadvantage": -1.5858,
      "matches": 32850
    },
    {
      "opponent": "dazzle",
      "winrate": 45.0634,
      "disadvantage": -3.4136,
      "matches": 14970
    },
    {
      "opponent": "death-prophet",
      "winrate": 45.1276,
      "disadvantage": 0.4434,
      "matches": 10929
    },
    {
      "opponent": "disruptor",
      "winrate": 41.7055,
      "disadvantage": 0.6756,
      "matches": 27663
    },
    {
      "opponent": "dragon-knight",
      "winrate": 44.7241,
      "disadvantage": -1.3536,
      "matches": 21532
    },
    {
      "opponent": "drow-ranger",
      "winrate": 42.8377,
      "disadvantage": 0.3684,
      "matches": 27938
    },
    {
      "opponent": "earth-spirit",
      "winrate": 44.8281,
      "disadvantage": -0.5065,
      "matches": 6545
    },
    {
      "opponent": "earthshaker",
      "winrate": 41.6122,
      "disadvantage": 0.0507,
      "matches": 77989
    },
    {
      "opponent": "elder-titan",
      "winrate": 48.9568,
      "disadvantage": -5.5397,
      "matches": 4122
    },
    {
      "opponent": "ember-spirit",
      "winrate": 46.4382,
      "disadvantage": -0.7972,
      "matches": 13224
    },
    {
      "opponent": "enchantress",
      "winrate": 44.559,
      "disadvantage": -0.9345,
      "matches": 10081
    },
    {
      "opponent": "enigma",
      "winrate": 42.0717,
      "disadvantage": 1.176,
      "matches": 8785
    },
    {
      "opponent": "faceless-void",
      "winrate": 45.963,
      "disadvantage": -1.4832,
      "matches": 31930
    },
    {
      "opponent": "grimstroke",
      "winrate": 46.1372,
      "disadvantage": -1.5266,
      "matches": 10666
    },
    {
      "opponent": "gyrocopter",
      "winrate": 46.2451,
      "disadvantage": -0.7053,
      "matches": 15673
    },
    {
      "opponent": "hoodwink",
      "winrate": 45.5582,
      "disadvantage": -0.2734,
      "matches": 27084
    },
    {
      "opponent": "huskar",
      "winrate": 47.9253,
      "disadvantage": -3.6154,
      "matches": 18389
    },
    {
      "opponent": "invoker",
      "winrate": 42.7487,
      "disadvantage": 1.6159,
      "matches": 48874
    },
    {
      "opponent": "io",
      "winrate": 45.4419,
      "disadvantage": -1.439,
      "matches": 7218
    },
    {
      "opponent": "jakiro",
      "winrate": 45.4535,
      "disadvantage": 0.1888,
      "matches": 27098
    },
    {
      "opponent": "juggernaut",
      "winrate": 41.2057,
      "disadvantage": -1.1897,
      "matches": 56463
    },
    {
      "opponent": "keeper-of-the-light",
      "winrate": 49.7849,
      "disadvantage": -3.6717,
      "matches": 6277
    },
    {
      "opponent": "kez",
      "winrate": 44.4985,
      "disadvantage": 0.8569,
      "matches": 8016
    },
    {
      "opponent": "kunkka",
      "winrate": 44.9135,
      "disadvantage": 0.0958,
      "matches": 12435
    },
    {
      "opponent": "legion-commander",
      "winrate": 40.453,
      "disadvantage": 0.7828,
      "matches": 53457
    },
    {
      "opponent": "leshrac",
      "winrate": 42.0239,
      "disadvantage": -0.3255,
      "matches": 15277
    },
    {
      "opponent": "lich",
      "winrate": 41.1688,
      "disadvantage": -0.5058,
      "matches": 28609
    },
    {
      "opponent": "lifestealer",
      "winrate": 44.4334,
      "disadvantage": -2.9429,
      "matches": 28249
    },
    {
      "opponent": "lina",
      "winrate": 47.0329,
      "disadvantage": 0.7195,
      "matches": 23003
    },
    {
      "opponent": "lion",
      "winrate": 43.9138,
      "disadvantage": -0.2174,
      "matches": 70356
    },
    {
      "opponent": "lone-druid",
      "winrate": 41.8647,
      "disadvantage": 0.5871,
      "matches": 5931
    },
    {
      "opponent": "luna",
      "winrate": 42.0522,
      "disadvantage": 1.5283,
      "matches": 21761
    },
    {
      "opponent": "lycan",
      "winrate": 46.3386,
      "disadvantage": -2.4414,
      "matches": 8699
    },
    {
      "opponent": "magnus",
      "winrate": 44.1111,
      "disadvantage": 0.2096,
      "matches": 41935
    },
    {
      "opponent": "marci",
      "winrate": 42.4129,
      "disadvantage": 1.7486,
      "matches": 23059
    },
    {
      "opponent": "mars",
      "winrate": 45.5459,
      "disadvantage": -0.3393,
      "matches": 32734
    },
    {
      "opponent": "medusa",
      "winrate": 38.2759,
      "disadvantage": 3.007,
      "matches": 36566
    },
    {
      "opponent": "meepo",
      "winrate": 37.7037,
      "disadvantage": 1.596,
      "matches": 5583
    },
    {
      "opponent": "mirana",
      "winrate": 42.8571,
      "disadvantage": -0.0253,
      "matches": 15351
    },
    {
      "opponent": "monkey-king",
      "winrate": 50.6027,
      "disadvantage": -0.4442,
      "matches": 20904
    },
    {
      "opponent": "morphling",
      "winrate": 49.3858,
      "disadvantage": -1.9606,
      "matches": 13921
    },
    {
      "opponent": "muerta",
      "winrate": 46.3936,
      "disadvantage": -1.0857,
      "matches": 11036
    },
    {
      "opponent": "naga-siren",
      "winrate": 46.4626,
      "disadvantage": -0.1351,
      "matches": 3986
    },
    {
      "opponent": "natures-prophet",
      "winrate": 43.9173,
      "disadvantage": 1.6032,
      "matches": 48252
    },
    {
      "opponent": "necrophos",
      "winrate": 44.0448,
      "disadvantage": -3.4443,
      "matches": 44902
    },
    {
      "opponent": "night-stalker",
      "winrate": 42.4956,
      "disadvantage": 0.3618,
      "matches": 13079
    },
    {
      "opponent": "nyx-assassin",
      "winrate": 41.2684,
      "disadvantage": -0.1818,
      "matches": 18353
    },
    {
      "opponent": "ogre-magi",
      "winrate": 42.0428,
      "disadvantage": 0.4971,
      "matches": 51966
    },
    {
      "opponent": "omniknight",
      "winrate": 45.05,
      "disadvantage": -2.7531,
      "matches": 7798
    },
    {
      "opponent": "oracle",
      "winrate": 42.3827,
      "disadvantage": -1.3732,
      "matches": 13942
    },
    {
      "opponent": "outworld-destroyer",
      "winrate": 41.5517,
      "disadvantage": 0.4249,
      "matches": 17477
    },
    {
      "opponent": "pangolier",
      "winrate": 49.5519,
      "disadvantage": -0.6159,
      "matches": 8034
    },
    {
      "opponent": "phantom-assassin",
      "winrate": 47.277,
      "disadvantage": -0.7274,
      "matches": 31326
    },
    {
      "opponent": "phantom-lancer",
      "winrate": 42.4039,
      "disadvantage": 0.3113,
      "matches": 19260
    },
    {
      "opponent": "phoenix",
      "winrate": 43.6163,
      "disadvantage": -0.1186,
      "matches": 14075
    },
    {
      "opponent": "primal-beast",
      "winrate": 46.2982,
      "disadvantage": -0.3564,
      "matches": 8631
    },
    {
      "opponent": "puck",
      "winrate": 44.5481,
      "disadvantage": 0.459,
      "matches": 24524
    },
    {
      "opponent": "pudge",
      "winrate": 42.0202,
      "disadvantage": -0.0754,
      "matches": 74507
    },
    {
      "opponent": "pugna",
      "winrate": 43.671,
      "disadvantage": -0.9727,
      "matches": 25399
    },
    {
      "opponent": "queen-of-pain",
      "winrate": 42.6118,
      "disadvantage": 0.5093,
      "matches": 52009
    },
    {
      "opponent": "razor",
      "winrate": 45.1702,
      "disadvantage": -1.3624,
      "matches": 15767
    },
    {
      "opponent": "riki",
      "winrate": 44.2536,
      "disadvantage": -0.1107,
      "matches": 11590
    },
    {
      "opponent": "ringmaster",
      "winrate": 46.5702,
      "disadvantage": 0.4328,
      "matches": 7260
    },
    {
      "opponent": "rubick",
      "winrate": 44.4811,
      "disadvantage": 1.3882,
      "matches": 49032
    },
    {
      "opponent": "sand-king",
      "winrate": 42.8015,
      "disadvantage": 0.4312,
      "matches": 28541
    },
    {
      "opponent": "shadow-demon",
      "winrate": 45.5028,
      "disadvantage": -0.3497,
      "matches": 9973
    },
    {
      "opponent": "shadow-fiend",
      "winrate": 45.0459,
      "disadvantage": 0.5221,
      "matches": 47789
    },
    {
      "opponent": "shadow-shaman",
      "winrate": 41.3732,
      "disadvantage": 0.6267,
      "matches": 42032
    },
    {
      "opponent": "silencer",
      "winrate": 40.3034,
      "disadvantage": 0.5,
      "matches": 46666
    },
    {
      "opponent": "skywrath-mage",
      "winrate": 41.9636,
      "disadvantage": 0.4619,
      "matches": 36646
    },
    {
      "opponent": "slardar",
      "winrate": 41.4451,
      "disadvantage": -0.7374,
      "matches": 26599
    },
    {
      "opponent": "slark",
      "winrate": 46.4444,
      "disadvantage": -1.1223,
      "matches": 27506
    },
    {
      "opponent": "snapfire",
      "winrate": 44.1248,
      "disadvantage": -0.4685,
      "matches": 33301
    },
    {
      "opponent": "sniper",
      "winrate": 44.863,
      "disadvantage": 0.2879,
      "matches": 53358
    },
    {
      "opponent": "spectre",
      "winrate": 40.0426,
      "disadvantage": 1.9224,
      "matches": 22049
    },
    {
      "opponent": "spirit-breaker",
      "winrate": 42.0774,
      "disadvantage": 0.1585,
      "matches": 30855
    },
    {
      "opponent": "storm-spirit",
      "winrate": 45.1281,
      "disadvantage": -0.0385,
      "matches": 20167
    },
    {
      "opponent": "sven",
      "winrate": 43.8734,
      "disadvantage": -0.1738,
      "matches": 36464
    },
    {
      "opponent": "techies",
      "winrate": 46.3741,
      "disadvantage": -0.2304,
      "matches": 23815
    },
    {
      "opponent": "templar-assassin",
      "winrate": 47.9135,
      "disadvantage": -1.5934,
      "matches": 19099
    },
    {
      "opponent": "terrorblade",
      "winrate": 47.1277,
      "disadvantage": -0.3055,
      "matches": 12638
    },
    {
      "opponent": "tidehunter",
      "winrate": 44.2716,
      "disadvantage": -0.6409,
      "matches": 16401
    },
    {
      "opponent": "timbersaw",
      "winrate": 46.781,
      "disadvantage": -1.81,
      "matches": 16667
    },
    {
      "opponent": "tinker",
      "winrate": 47.6882,
      "disadvantage": -0.4354,
      "matches": 19055
    },
    {
      "opponent": "tiny",
      "winrate": 50.1205,
      "disadvantage": -1.524,
      "matches": 14934
    },
    {
      "opponent": "treant-protector",
      "winrate": 47.4515,
      "disadvantage": -3.1919,
      "matches": 9692
    },
    {
      "opponent": "troll-warlord",
      "winrate": 45.97,
      "disadvantage": -3.5148,
      "matches": 15906
    },
    {
      "opponent": "tusk",
      "winrate": 47.805,
      "disadvantage": -0.9666,
      "matches": 13827
    },
    {
      "opponent": "underlord",
      "winrate": 45.4808,
      "disadvantage": -0.7299,
      "matches": 11739
    },
    {
      "opponent": "undying",
      "winrate": 42.6672,
      "disadvantage": -0.1885,
      "matches": 27534
    },
    {
      "opponent": "ursa",
      "winrate": 42.9581,
      "disadvantage": -0.6238,
      "matches": 41026
    },
    {
      "opponent": "vengeful-spirit",
      "winrate": 39.6095,
      "disadvantage": -0.1471,
      "matches": 30629
    },
    {
      "opponent": "venomancer",
      "winrate": 41.2814,
      "disadvantage": 0.6104,
      "matches": 28187
    },
    {
      "opponent": "viper",
      "winrate": 44.4782,
      "disadvantage": -0.0456,
      "matches": 17069
    },
    {
      "opponent": "visage",
      "winrate": 41.3323,
      "disadvantage": 1.5126,
      "matches": 2792
    },
    {
      "opponent": "void-spirit",
      "winrate": 43.3033,
      "disadvantage": -0.8276,
      "matches": 13350
    },
    {
      "opponent": "warlock",
      "winrate": 43.6512,
      "disadvantage": -1.0822,
      "matches": 20437
    },
    {
      "opponent": "weaver",
      "winrate": 41.9615,
      "disadvantage": 1.5814,
      "matches": 31455
    },
    {
      "opponent": "windranger",
      "winrate": 43.4476,
      "disadvantage": 1.0497,
      "matches": 33965
    },
    {
      "opponent": "winter-wyvern",
      "winrate": 42.3618,
      "disadvantage": -0.5895,
      "matches": 10441
    },
    {
      "opponent": "witch-doctor",
      "winrate": 39.5466,
      "disadvantage": 1.2023,
      "matches": 50424
    },
    {
      "opponent": "wraith-king",
      "winrate": 37.9976,
      "disadvantage": 1.5093,
      "matches": 38384
    },
    {
      "opponent": "zeus",
      "winrate": 42.2962,
      "disadvantage": 0.8293,
      "matches": 38280
    }
  ]
}