{
  "hero": "keeper-of-the-light",
  "patch": "7.39D",
  "updated_at": "2025-09-09T14:14:22Z",
  "matchups": [
    {
      "opponent": "abaddon",
      "winrate": 47.2194,
      "disadvantage": -2.7482,
      "matches": 11940
    },
    {
      "opponent": "alchemist",
      "winrate": 45.4981,
      "disadvantage": 1.438,
      "matches": 9596
    },
    {
      "opponent": "ancient-apparition",
      "winrate": 45.3404,
      "disadvantage": 1.3695,
      "matches": 13703
    },
    {
      "opponent": "anti-mage",
      "winrate": 44.2947,
      "disadvantage": 1.3924,
      "matches": 29245
    },
    {
      "opponent": "arc-warden",
      "winrate": 48.3251,
      "disadvantage": -1.096,
      "matches": 5314
    },
    {
      "opponent": "axe",
      "winrate": 46.9907,
      "disadvantage": -0.5918,
      "matches": 36537
    },
    {
      "opponent": "bane",
      "winrate": 47.9193,
      "disadvantage": 0.2601,
      "matches": 5503
    },
    {
      "opponent": "batrider",
      "winrate": 53.0465,
      "disadvantage": -0.3068,
      "matches": 3627
    },
    {
      "opponent": "beastmaster",
      "winrate": 54.3838,
      "disadvantage": -2.4549,
      "matches": 6524
    },
    {
      "opponent": "bloodseeker",
      "winrate": 47.5166,
      "disadvantage": 0.5968,
      "matches": 6141
    },
    {
      "opponent": "bounty-hunter",
      "winrate": 47.8876,
      "disadvantage": 0.3714,
      "matches": 8403
    },
    {
      "opponent": "brewmaster",
      "winrate": 48.4442,
      "disadvantage": -0.404,
      "matches": 2089
    },
    {
      "opponent": "bristleback",
      "winrate": 51.0594,
      "disadvantage": 1.3202,
      "matches": 9769
    },
    {
      "opponent": "broodmother",
      "winrate": 46.0656,
      "disadvantage": -1.345,
      "matches": 4969
    },
    {
      "opponent": "centaur-warrunner",
      "winrate": 45.9695,
      "disadvantage": 0.3623,
      "matches": 10892
    },
    {
      "opponent": "chaos-knight",
      "winrate": 43.5141,
      "disadvantage": 2.636,
      "matches": 9089
    },
    {
      "opponent": "chen",
      "winrate": 43.1372,
      "disadvantage": 7.7359,
      "matches": 1734
    },
    {
      "opponent": "clinkz",
      "winrate": 42.4812,
      "disadvantage": 3.2889,
      "matches": 8133
    },
    {
      "opponent": "clockwerk",
      "winrate": 45.5893,
      "disadvantage": 1.1071,
      "matches": 8967
    },
    {
      "opponent": "crystal-maiden",
      "winrate": 46.0209,
      "disadvantage": 2.129,
      "matches": 18346
    },
    {
      "opponent": "dark-seer",
      "winrate": 42.0905,
      "disadvantage": 5.8577,
      "matches": 3578
    },
    {
      "opponent": "dark-willow",
      "winrate": 47.7462,
      "disadvantage": 1.0576,
      "matches": 9961
    },
    {
      "opponent": "dawnbreaker",
      "winrate": 46.0221,
      "disadvantage": -1.2274,
      "matches": 20903
    },
    {
      "opponent": "dazzle",
      "winrate": 48.4133,
      "disadvantage": -2.5589,
      "matches": 11187
    },
    {
      "opponent": "death-prophet",
      "winrate": 51.4419,
      "disadvantage": -1.438,
      "matches": 6172
    },
    {
      "opponent": "disruptor",
      "winrate": 45.815,
      "disadvantage": 0.7432,
      "matches": 13919
    },
    {
      "opponent": "doom",
      "winrate": 52.0313,
      "disadvantage": 2.2922,
      "matches": 7778
    },
    {
      "opponent": "dragon-knight",
      "winrate": 48.5041,
      "disadvantage": -0.7256,
      "matches": 10061
    },
    {
      "opponent": "drow-ranger",
      "winrate": 47.6357,
      "disadvantage": -0.7552,
      "matches": 21614
    },
    {
      "opponent": "earth-spirit",
      "winrate": 48.0725,
      "disadvantage": 0.3616,
      "matches": 4851
    },
    {
      "opponent": "earthshaker",
      "winrate": 46.805,
      "disadvantage": -0.0193,
      "matches": 30533
    },
    {
      "opponent": "elder-titan",
      "winrate": 50.0,
      "disadvantage": -1.5349,
      "matches": 2438
    },
    {
      "opponent": "ember-spirit",
      "winrate": 49.7255,
      "disadvantage": 0.1264,
      "matches": 8927
    },
    {
      "opponent": "enchantress",
      "winrate": 43.6218,
      "disadvantage": 3.7796,
      "matches": 5268
    },
    {
      "opponent": "enigma",
      "winrate": 47.4944,
      "disadvantage": -0.1941,
      "matches": 5428
    },
    {
      "opponent": "faceless-void",
      "winrate": 46.3354,
      "disadvantage": 2.1169,
      "matches": 16100
    },
    {
      "opponent": "grimstroke",
      "winrate": 50.1889,
      "disadvantage": -1.4558,
      "matches": 7143
    },
    {
      "opponent": "gyrocopter",
      "winrate": 47.2228,
      "disadvantage": 2.1907,
      "matches": 9290
    },
    {
      "opponent": "hoodwink",
      "winrate": 49.3939,
      "disadvantage": 0.1062,
      "matches": 15593
    },
    {
      "opponent": "huskar",
      "winrate": 47.4076,
      "disadvantage": 1.4733,
      "matches": 11013
    },
    {
      "opponent": "invoker",
      "winrate": 49.4535,
      "disadvantage": -1.1846,
      "matches": 33395
    },
    {
      "opponent": "io",
      "winrate": 49.6425,
      "disadvantage": -1.6188,
      "matches": 5455
    },
    {
      "opponent": "jakiro",
      "winrate": 49.8922,
      "disadvantage": 0.0428,
      "matches": 18562
    },
    {
      "opponent": "juggernaut",
      "winrate": 43.7099,
      "disadvantage": 1.0673,
      "matches": 31041
    },
    {
      "opponent": "kez",
      "winrate": 48.4237,
      "disadvantage": 1.6031,
      "matches": 6154
    },
    {
      "opponent": "kunkka",
      "winrate": 50.017,
      "disadvantage": -1.0435,
      "matches": 8811
    },
    {
      "opponent": "legion-commander",
      "winrate": 44.4628,
      "disadvantage": 1.0525,
      "matches": 33898
    },
    {
      "opponent": "leshrac",
      "winrate": 47.7128,
      "disadvantage": -1.5506,
      "matches": 8482
    },
    {
      "opponent": "lich",
      "winrate": 45.2688,
      "disadvantage": -0.4849,
      "matches": 18748
    },
    {
      "opponent": "lifestealer",
      "winrate": 45.6165,
      "disadvantage": 0.1718,
      "matches": 15764
    },
    {
      "opponent": "lina",
      "winrate": 50.9063,
      "disadvantage": 0.7406,
      "matches": 15998
    },
    {
      "opponent": "lion",
      "winrate": 48.5653,
      "disadvantage": -0.4504,
      "matches": 47748
    },
    {
      "opponent": "lone-druid",
      "winrate": 48.5778,
      "disadvantage": -2.2105,
      "matches": 3129
    },
    {
      "opponent": "luna",
      "winrate": 48.1556,
      "disadvantage": -0.642,
      "matches": 13365
    },
    {
      "opponent": "lycan",
      "winrate": 40.7897,
      "disadvantage": 6.5604,
      "matches": 4609
    },
    {
      "opponent": "magnus",
      "winrate": 47.7803,
      "disadvantage": 0.3528,
      "matches": 23405
    },
    {
      "opponent": "marci",
      "winrate": 47.8003,
      "disadvantage": 0.1259,
      "matches": 14207
    },
    {
      "opponent": "mars",
      "winrate": 48.2712,
      "disadvantage": 0.7608,
      "matches": 14085
    },
    {
      "opponent": "medusa",
      "winrate": 44.9725,
      "disadvantage": 0.5043,
      "matches": 14938
    },
    {
      "opponent": "meepo",
      "winrate": 44.1097,
      "disadvantage": -0.8753,
      "matches": 4813
    },
    {
      "opponent": "mirana",
      "winrate": 46.321,
      "disadvantage": 0.6559,
      "matches": 8739
    },
    {
      "opponent": "monkey-king",
      "winrate": 55.5153,
      "disadvantage": -1.8151,
      "matches": 12447
    },
    {
      "opponent": "morphling",
      "winrate": 53.3027,
      "disadvantage": -1.7524,
      "matches": 9795
    },
    {
      "opponent": "muerta",
      "winrate": 48.5218,
      "disadvantage": 0.6497,
      "matches": 6968
    },
    {
      "opponent": "naga-siren",
      "winrate": 43.1904,
      "disadvantage": 5.7788,
      "matches": 3172
    },
    {
      "opponent": "natures-prophet",
      "winrate": 50.3919,
      "disadvantage": -1.1452,
      "matches": 31888
    },
    {
      "opponent": "necrophos",
      "winrate": 47.3252,
      "disadvantage": -2.3948,
      "matches": 25722
    },
    {
      "opponent": "night-stalker",
      "winrate": 47.4082,
      "disadvantage": 0.1203,
      "matches": 7003
    },
    {
      "opponent": "nyx-assassin",
      "winrate": 43.4434,
      "disadvantage": 1.9772,
      "matches": 10867
    },
    {
      "opponent": "ogre-magi",
      "winrate": 45.8182,
      "disadvantage": 1.2499,
      "matches": 29593
    },
    {
      "opponent": "omniknight",
      "winrate": 43.3797,
      "disadvantage": 3.4189,
      "matches": 5030
    },
    {
      "opponent": "oracle",
      "winrate": 44.1458,
      "disadvantage": 1.0198,
      "matches": 9267
    },
    {
      "opponent": "outworld-destroyer",
      "winrate": 45.763,
      "disadvantage": 0.3115,
      "matches": 11258
    },
    {
      "opponent": "pangolier",
      "winrate": 50.8426,
      "disadvantage": 1.7276,
      "matches": 3501
    },
    {
      "opponent": "phantom-assassin",
      "winrate": 49.8024,
      "disadvantage": 1.1544,
      "matches": 21768
    },
    {
      "opponent": "phantom-lancer",
      "winrate": 46.7139,
      "disadvantage": 0.0069,
      "matches": 14805
    },
    {
      "opponent": "phoenix",
      "winrate": 48.8557,
      "disadvantage": -1.8164,
      "matches": 7166
    },
    {
      "opponent": "primal-beast",
      "winrate": 51.1575,
      "disadvantage": -0.859,
      "matches": 4838
    },
    {
      "opponent": "puck",
      "winrate": 50.2573,
      "disadvantage": -1.2458,
      "matches": 14378
    },
    {
      "opponent": "pudge",
      "winrate": 45.9761,
      "disadvantage": 0.1463,
      "matches": 49319
    },
    {
      "opponent": "pugna",
      "winrate": 47.2992,
      "disadvantage": -0.2445,
      "matches": 13015
    },
    {
      "opponent": "queen-of-pain",
      "winrate": 47.111,
      "disadvantage": 0.4499,
      "matches": 30322
    },
    {
      "opponent": "razor",
      "winrate": 48.1365,
      "disadvantage": -0.1634,
      "matches": 8586
    },
    {
      "opponent": "riki",
      "winrate": 49.3204,
      "disadvantage": -0.895,
      "matches": 8903
    },
    {
      "opponent": "ringmaster",
      "winrate": 52.7784,
      "disadvantage": -2.0587,
      "matches": 4301
    },
    {
      "opponent": "rubick",
      "winrate": 51.3481,
      "disadvantage": -1.8552,
      "matches": 30782
    },
    {
      "opponent": "sand-king",
      "winrate": 48.5441,
      "disadvantage": -1.036,
      "matches": 7865
    },
    {
      "opponent": "shadow-demon",
      "winrate": 47.2299,
      "disadvantage": 1.8431,
      "matches": 4296
    },
    {
      "opponent": "shadow-fiend",
      "winrate": 51.2241,
      "disadvantage": -1.9921,
      "matches": 34921
    },
    {
      "opponent": "shadow-shaman",
      "winrate": 45.6649,
      "disadvantage": 0.8235,
      "matches": 31072
    },
    {
      "opponent": "silencer",
      "winrate": 45.16,
      "disadvantage": -0.0204,
      "matches": 28244
    },
    {
      "opponent": "skywrath-mage",
      "winrate": 46.374,
      "disadvantage": 0.5149,
      "matches": 23828
    },
    {
      "opponent": "slardar",
      "winrate": 42.906,
      "disadvantage": 2.6394,
      "matches": 13730
    },
    {
      "opponent": "slark",
      "winrate": 48.1845,
      "disadvantage": 0.9453,
      "matches": 15974
    },
    {
      "opponent": "snapfire",
      "winrate": 49.8968,
      "disadvantage": -0.8594,
      "matches": 11638
    },
    {
      "opponent": "sniper",
      "winrate": 48.928,
      "disadvantage": 0.3387,
      "matches": 35123
    },
    {
      "opponent": "spectre",
      "winrate": 47.5544,
      "disadvantage": -1.6251,
      "matches": 14005
    },
    {
      "opponent": "spirit-breaker",
      "winrate": 44.8134,
      "disadvantage": 2.1903,
      "matches": 19512
    },
    {
      "opponent": "storm-spirit",
      "winrate": 47.8143,
      "disadvantage": 1.3411,
      "matches": 13360
    },
    {
      "opponent": "sven",
      "winrate": 45.9202,
      "disadvantage": 1.4962,
      "matches": 15577
    },
    {
      "opponent": "techies",
      "winrate": 50.8391,
      "disadvantage": -0.3838,
      "matches": 18293
    },
    {
      "opponent": "templar-assassin",
      "winrate": 50.4709,
      "disadvantage": 0.2017,
      "matches": 11890
    },
    {
      "opponent": "terrorblade",
      "winrate": 52.1177,
      "disadvantage": -1.7655,
      "matches": 7508
    },
    {
      "opponent": "tidehunter",
      "winrate": 46.9578,
      "disadvantage": 0.4739,
      "matches": 10075
    },
    {
      "opponent": "timbersaw",
      "winrate": 49.7831,
      "disadvantage": -0.5961,
      "matches": 10837
    },
    {
      "opponent": "tinker",
      "winrate": 50.3069,
      "disadvantage": -0.2263,
      "matches": 10913
    },
    {
      "opponent": "tiny",
      "winrate": 52.6208,
      "disadvantage": 0.2323,
      "matches": 8871
    },
    {
      "opponent": "treant-protector",
      "winrate": 49.4105,
      "disadvantage": -1.1009,
      "matches": 6023
    },
    {
      "opponent": "troll-warlord",
      "winrate": 48.6313,
      "disadvantage": -1.6804,
      "matches": 6868
    },
    {
      "opponent": "tusk",
      "winrate": 49.7422,
      "disadvantage": 1.334,
      "matches": 8729
    },
    {
      "opponent": "underlord",
      "winrate": 50.2106,
      "disadvantage": -1.5095,
      "matches": 5698
    },
    {
      "opponent": "undying",
      "winrate": 46.9045,
      "disadvantage": -0.5317,
      "matches": 18608
    },
    {
      "opponent": "ursa",
      "winrate": 46.9188,
      "disadvantage": -0.1895,
      "matches": 20382
    },
    {
      "opponent": "vengeful-spirit",
      "winrate": 44.1422,
      "disadvantage": -0.7339,
      "matches": 20887
    },
    {
      "opponent": "venomancer",
      "winrate": 46.7511,
      "disadvantage": -0.5095,
      "matches": 17437
    },
    {
      "opponent": "viper",
      "winrate": 48.9832,
      "disadvantage": -0.1712,
      "matches": 11753
    },
    {
      "opponent": "visage",
      "winrate": 49.2753,
      "disadvantage": -2.4112,
      "matches": 2484
    },
    {
      "opponent": "void-spirit",
      "winrate": 46.7315,
      "disadvantage": -0.3265,
      "matches": 7190
    },
    {
      "opponent": "warlock",
      "winrate": 48.0595,
      "disadvantage": -1.6612,
      "matches": 13038
    },
    {
      "opponent": "weaver",
      "winrate": 46.1617,
      "disadvantage": 1.5861,
      "matches": 19436
    },
    {
      "opponent": "windranger",
      "winrate": 48.2635,
      "disadvantage": 0.5035,
      "matches": 23179
    },
    {
      "opponent": "winter-wyvern",
      "winrate": 46.5299,
      "disadvantage": -0.7701,
      "matches": 6974
    },
    {
      "opponent": "witch-doctor",
      "winrate": 45.3502,
      "disadvantage": -0.8797,
      "matches": 37905
    },
    {
      "opponent": "wraith-king",
      "winrate": 46.3957,
      "disadvantage": -2.9849,
      "matches": 22515
    },
    {
      "opponent": "zeus",
      "winrate": 48.642,
      "disadvantage": -1.2849,
      "matches": 24117
    }
  ]
}