{
  "hero": "troll-warlord",
  "patch": "7.39D",
  "updated_at": "2025-09-22T14:19:24Z",
  "matchups": [
    {
      "opponent": "abaddon",
      "winrate": 45.8127,
      "disadvantage": 2.1113,
      "matches": 23655
    },
    {
      "opponent": "alchemist",
      "winrate": 49.2558,
      "disadvantage": 0.882,
      "matches": 22509
    },
    {
      "opponent": "ancient-apparition",
      "winrate": 47.2226,
      "disadvantage": 2.6225,
      "matches": 24340
    },
    {
      "opponent": "anti-mage",
      "winrate": 52.8179,
      "disadvantage": -4.2189,
      "matches": 65207
    },
    {
      "opponent": "arc-warden",
      "winrate": 49.7224,
      "disadvantage": 0.7591,
      "matches": 8648
    },
    {
      "opponent": "axe",
      "winrate": 45.731,
      "disadvantage": 3.9204,
      "matches": 60167
    },
    {
      "opponent": "bane",
      "winrate": 49.8312,
      "disadvantage": 1.3075,
      "matches": 10371
    },
    {
      "opponent": "batrider",
      "winrate": 55.2553,
      "disadvantage": 0.8407,
      "matches": 6698
    },
    {
      "opponent": "beastmaster",
      "winrate": 56.8709,
      "disadvantage": -1.2755,
      "matches": 16548
    },
    {
      "opponent": "bloodseeker",
      "winrate": 54.0984,
      "disadvantage": -2.5315,
      "matches": 13810
    },
    {
      "opponent": "bounty-hunter",
      "winrate": 52.4829,
      "disadvantage": -1.0461,
      "matches": 18164
    },
    {
      "opponent": "brewmaster",
      "winrate": 49.7104,
      "disadvantage": 1.6344,
      "matches": 4317
    },
    {
      "opponent": "bristleback",
      "winrate": 54.2111,
      "disadvantage": 1.1786,
      "matches": 25480
    },
    {
      "opponent": "broodmother",
      "winrate": 48.2348,
      "disadvantage": -0.002,
      "matches": 8328
    },
    {
      "opponent": "centaur-warrunner",
      "winrate": 47.7788,
      "disadvantage": 1.5814,
      "matches": 24919
    },
    {
      "opponent": "chaos-knight",
      "winrate": 49.339,
      "disadvantage": 0.0037,
      "matches": 19593
    },
    {
      "opponent": "chen",
      "winrate": 50.1071,
      "disadvantage": 4.5329,
      "matches": 3267
    },
    {
      "opponent": "clinkz",
      "winrate": 47.4466,
      "disadvantage": 1.2848,
      "matches": 17820
    },
    {
      "opponent": "clockwerk",
      "winrate": 48.2132,
      "disadvantage": 1.4543,
      "matches": 17014
    },
    {
      "opponent": "crystal-maiden",
      "winrate": 50.2026,
      "disadvantage": 1.1371,
      "matches": 35524
    },
    {
      "opponent": "dark-seer",
      "winrate": 48.8872,
      "disadvantage": 2.5702,
      "matches": 6695
    },
    {
      "opponent": "dark-willow",
      "winrate": 50.0954,
      "disadvantage": 1.8643,
      "matches": 17812
    },
    {
      "opponent": "dawnbreaker",
      "winrate": 49.1368,
      "disadvantage": -1.2768,
      "matches": 38753
    },
    {
      "opponent": "dazzle",
      "winrate": 51.085,
      "disadvantage": -1.9849,
      "matches": 19906
    },
    {
      "opponent": "death-prophet",
      "winrate": 53.4817,
      "disadvantage": -0.304,
      "matches": 13786
    },
    {
      "opponent": "disruptor",
      "winrate": 49.099,
      "disadvantage": 0.6064,
      "matches": 29247
    },
    {
      "opponent": "doom",
      "winrate": 53.3957,
      "disadvantage": 4.1644,
      "matches": 14960
    },
    {
      "opponent": "dragon-knight",
      "winrate": 51.5377,
      "disadvantage": -0.6614,
      "matches": 23899
    },
    {
      "opponent": "drow-ranger",
      "winrate": 48.9418,
      "disadvantage": 1.4329,
      "matches": 40211
    },
    {
      "opponent": "earth-spirit",
      "winrate": 53.9529,
      "disadvantage": -2.1934,
      "matches": 8424
    },
    {
      "opponent": "earthshaker",
      "winrate": 48.8888,
      "disadvantage": 0.4467,
      "matches": 79693
    },
    {
      "opponent": "elder-titan",
      "winrate": 53.5261,
      "disadvantage": -2.456,
      "matches": 5048
    },
    {
      "opponent": "ember-spirit",
      "winrate": 56.0665,
      "disadvantage": -2.9851,
      "matches": 16047
    },
    {
      "opponent": "enchantress",
      "winrate": 49.0723,
      "disadvantage": 1.8466,
      "matches": 13260
    },
    {
      "opponent": "enigma",
      "winrate": 51.1712,
      "disadvantage": -0.6028,
      "matches": 10971
    },
    {
      "opponent": "faceless-void",
      "winrate": 51.8219,
      "disadvantage": -0.1989,
      "matches": 38970
    },
    {
      "opponent": "grimstroke",
      "winrate": 51.5875,
      "disadvantage": 0.3312,
      "matches": 14015
    },
    {
      "opponent": "gyrocopter",
      "winrate": 51.3144,
      "disadvantage": 1.3907,
      "matches": 18753
    },
    {
      "opponent": "hoodwink",
      "winrate": 51.8499,
      "disadvantage": 0.8398,
      "matches": 34704
    },
    {
      "opponent": "huskar",
      "winrate": 54.8067,
      "disadvantage": -2.9117,
      "matches": 24039
    },
    {
      "opponent": "invoker",
      "winrate": 49.9696,
      "disadvantage": 1.6931,
      "matches": 57601
    },
    {
      "opponent": "io",
      "winrate": 54.138,
      "disadvantage": -2.7424,
      "matches": 10355
    },
    {
      "opponent": "jakiro",
      "winrate": 52.2854,
      "disadvantage": 0.834,
      "matches": 33342
    },
    {
      "opponent": "juggernaut",
      "winrate": 48.6369,
      "disadvantage": -1.1118,
      "matches": 73070
    },
    {
      "opponent": "keeper-of-the-light",
      "winrate": 51.9486,
      "disadvantage": 1.4994,
      "matches": 8185
    },
    {
      "opponent": "kez",
      "winrate": 56.0373,
      "disadvantage": -3.1469,
      "matches": 11023
    },
    {
      "opponent": "kunkka",
      "winrate": 51.7658,
      "disadvantage": 0.5524,
      "matches": 15630
    },
    {
      "opponent": "legion-commander",
      "winrate": 49.5261,
      "disadvantage": -1.0773,
      "matches": 74597
    },
    {
      "opponent": "leshrac",
      "winrate": 49.7019,
      "disadvantage": -0.5896,
      "matches": 15267
    },
    {
      "opponent": "lich",
      "winrate": 48.0159,
      "disadvantage": -0.1251,
      "matches": 36567
    },
    {
      "opponent": "lifestealer",
      "winrate": 50.2463,
      "disadvantage": -1.3468,
      "matches": 38158
    },
    {
      "opponent": "lina",
      "winrate": 53.9713,
      "disadvantage": 1.0591,
      "matches": 31639
    },
    {
      "opponent": "lion",
      "winrate": 49.7964,
      "disadvantage": 1.533,
      "matches": 84024
    },
    {
      "opponent": "lone-druid",
      "winrate": 51.1383,
      "disadvantage": -1.2899,
      "matches": 7818
    },
    {
      "opponent": "luna",
      "winrate": 49.5361,
      "disadvantage": 1.2011,
      "matches": 26734
    },
    {
      "opponent": "lycan",
      "winrate": 52.8129,
      "disadvantage": -1.7561,
      "matches": 12389
    },
    {
      "opponent": "magnus",
      "winrate": 52.3451,
      "disadvantage": -0.908,
      "matches": 48184
    },
    {
      "opponent": "marci",
      "winrate": 55.2973,
      "disadvantage": -4.0411,
      "matches": 33479
    },
    {
      "opponent": "mars",
      "winrate": 51.8774,
      "disadvantage": 0.5846,
      "matches": 33689
    },
    {
      "opponent": "medusa",
      "winrate": 46.1007,
      "disadvantage": 2.4596,
      "matches": 35943
    },
    {
      "opponent": "meepo",
      "winrate": 52.569,
      "disadvantage": -6.1211,
      "matches": 8252
    },
    {
      "opponent": "mirana",
      "winrate": 49.7191,
      "disadvantage": 0.3753,
      "matches": 19226
    },
    {
      "opponent": "monkey-king",
      "winrate": 57.6158,
      "disadvantage": -0.1818,
      "matches": 28513
    },
    {
      "opponent": "morphling",
      "winrate": 55.9706,
      "disadvantage": -1.0667,
      "matches": 16464
    },
    {
      "opponent": "muerta",
      "winrate": 47.2952,
      "disadvantage": 5.2577,
      "matches": 15399
    },
    {
      "opponent": "naga-siren",
      "winrate": 47.9596,
      "disadvantage": 5.1865,
      "matches": 6249
    },
    {
      "opponent": "natures-prophet",
      "winrate": 52.0996,
      "disadvantage": 0.5724,
      "matches": 62319
    },
    {
      "opponent": "necrophos",
      "winrate": 46.6163,
      "disadvantage": 1.5538,
      "matches": 51025
    },
    {
      "opponent": "night-stalker",
      "winrate": 52.8393,
      "disadvantage": -2.3804,
      "matches": 15479
    },
    {
      "opponent": "nyx-assassin",
      "winrate": 49.4467,
      "disadvantage": -0.9814,
      "matches": 20604
    },
    {
      "opponent": "ogre-magi",
      "winrate": 48.0,
      "disadvantage": 2.1025,
      "matches": 61750
    },
    {
      "opponent": "omniknight",
      "winrate": 47.9932,
      "disadvantage": 1.7789,
      "matches": 10066
    },
    {
      "opponent": "oracle",
      "winrate": 46.972,
      "disadvantage": 1.3372,
      "matches": 15869
    },
    {
      "opponent": "outworld-destroyer",
      "winrate": 45.6023,
      "disadvantage": 3.704,
      "matches": 23001
    },
    {
      "opponent": "pangolier",
      "winrate": 55.9935,
      "disadvantage": 0.3193,
      "matches": 8651
    },
    {
      "opponent": "phantom-assassin",
      "winrate": 55.0654,
      "disadvantage": -1.0985,
      "matches": 48406
    },
    {
      "opponent": "phantom-lancer",
      "winrate": 49.9884,
      "disadvantage": -0.003,
      "matches": 25878
    },
    {
      "opponent": "phoenix",
      "winrate": 49.9916,
      "disadvantage": 0.6182,
      "matches": 18051
    },
    {
      "opponent": "primal-beast",
      "winrate": 53.4718,
      "disadvantage": 0.1122,
      "matches": 10441
    },
    {
      "opponent": "puck",
      "winrate": 53.0207,
      "disadvantage": -0.5894,
      "matches": 28519
    },
    {
      "opponent": "pudge",
      "winrate": 49.965,
      "disadvantage": -0.8195,
      "matches": 97204
    },
    {
      "opponent": "pugna",
      "winrate": 48.1322,
      "disadvantage": 2.0397,
      "matches": 28270
    },
    {
      "opponent": "queen-of-pain",
      "winrate": 50.8287,
      "disadvantage": -0.259,
      "matches": 58644
    },
    {
      "opponent": "razor",
      "winrate": 48.2777,
      "disadvantage": 2.8714,
      "matches": 20119
    },
    {
      "opponent": "riki",
      "winrate": 53.3829,
      "disadvantage": -1.8906,
      "matches": 16923
    },
    {
      "opponent": "ringmaster",
      "winrate": 52.1925,
      "disadvantage": 2.0083,
      "matches": 8871
    },
    {
      "opponent": "rubick",
      "winrate": 52.7236,
      "disadvantage": 0.262,
      "matches": 57257
    },
    {
      "opponent": "sand-king",
      "winrate": 52.0742,
      "disadvantage": -1.5855,
      "matches": 31071
    },
    {
      "opponent": "shadow-demon",
      "winrate": 51.164,
      "disadvantage": 1.4113,
      "matches": 10996
    },
    {
      "opponent": "shadow-fiend",
      "winrate": 53.7747,
      "disadvantage": -1.0415,
      "matches": 63435
    },
    {
      "opponent": "shadow-shaman",
      "winrate": 48.3442,
      "disadvantage": 1.0653,
      "matches": 53299
    },
    {
      "opponent": "silencer",
      "winrate": 47.9366,
      "disadvantage": 0.2424,
      "matches": 52949
    },
    {
      "opponent": "skywrath-mage",
      "winrate": 48.8918,
      "disadvantage": 0.9321,
      "matches": 44038
    },
    {
      "opponent": "slardar",
      "winrate": 50.9414,
      "disadvantage": -2.7845,
      "matches": 34999
    },
    {
      "opponent": "slark",
      "winrate": 49.484,
      "disadvantage": 3.142,
      "matches": 33140
    },
    {
      "opponent": "snapfire",
      "winrate": 51.8758,
      "disadvantage": -0.3931,
      "matches": 36196
    },
    {
      "opponent": "sniper",
      "winrate": 52.769,
      "disadvantage": -0.4027,
      "matches": 69014
    },
    {
      "opponent": "spectre",
      "winrate": 49.5737,
      "disadvantage": -0.4239,
      "matches": 26512
    },
    {
      "opponent": "spirit-breaker",
      "winrate": 49.9753,
      "disadvantage": -0.243,
      "matches": 40510
    },
    {
      "opponent": "storm-spirit",
      "winrate": 54.7799,
      "disadvantage": -2.4228,
      "matches": 24498
    },
    {
      "opponent": "sven",
      "winrate": 54.8678,
      "disadvantage": -4.2725,
      "matches": 48112
    },
    {
      "opponent": "techies",
      "winrate": 52.0928,
      "disadvantage": 1.6908,
      "matches": 33423
    },
    {
      "opponent": "templar-assassin",
      "winrate": 56.6272,
      "disadvantage": -2.7455,
      "matches": 25267
    },
    {
      "opponent": "terrorblade",
      "winrate": 53.1505,
      "disadvantage": 0.8751,
      "matches": 16489
    },
    {
      "opponent": "tidehunter",
      "winrate": 48.9581,
      "disadvantage": 1.8118,
      "matches": 18765
    },
    {
      "opponent": "timbersaw",
      "winrate": 55.057,
      "disadvantage": -2.6959,
      "matches": 19903
    },
    {
      "opponent": "tinker",
      "winrate": 51.3791,
      "disadvantage": 2.6884,
      "matches": 20049
    },
    {
      "opponent": "tiny",
      "winrate": 55.6568,
      "disadvantage": 0.3984,
      "matches": 17881
    },
    {
      "opponent": "treant-protector",
      "winrate": 50.9122,
      "disadvantage": 0.6251,
      "matches": 12551
    },
    {
      "opponent": "tusk",
      "winrate": 54.2441,
      "disadvantage": 0.0234,
      "matches": 15598
    },
    {
      "opponent": "underlord",
      "winrate": 50.7569,
      "disadvantage": 1.2083,
      "matches": 12881
    },
    {
      "opponent": "undying",
      "winrate": 50.5402,
      "disadvantage": -0.8267,
      "matches": 37390
    },
    {
      "opponent": "ursa",
      "winrate": 52.7867,
      "disadvantage": -3.1827,
      "matches": 57037
    },
    {
      "opponent": "vengeful-spirit",
      "winrate": 46.3549,
      "disadvantage": 0.3015,
      "matches": 38600
    },
    {
      "opponent": "venomancer",
      "winrate": 49.5021,
      "disadvantage": -0.2156,
      "matches": 34550
    },
    {
      "opponent": "viper",
      "winrate": 50.2658,
      "disadvantage": 1.6775,
      "matches": 25389
    },
    {
      "opponent": "visage",
      "winrate": 50.8603,
      "disadvantage": -0.7646,
      "matches": 3952
    },
    {
      "opponent": "void-spirit",
      "winrate": 53.0349,
      "disadvantage": -3.336,
      "matches": 15750
    },
    {
      "opponent": "warlock",
      "winrate": 50.7296,
      "disadvantage": -0.9893,
      "matches": 28029
    },
    {
      "opponent": "weaver",
      "winrate": 50.5469,
      "disadvantage": 0.2828,
      "matches": 40588
    },
    {
      "opponent": "windranger",
      "winrate": 50.32,
      "disadvantage": 1.5833,
      "matches": 44521
    },
    {
      "opponent": "winter-wyvern",
      "winrate": 46.8002,
      "disadvantage": 2.1931,
      "matches": 12829
    },
    {
      "opponent": "witch-doctor",
      "winrate": 47.6847,
      "disadvantage": 0.0895,
      "matches": 67508
    },
    {
      "opponent": "wraith-king",
      "winrate": 45.8522,
      "disadvantage": 0.8135,
      "matches": 43614
    },
    {
      "opponent": "zeus",
      "winrate": 50.5737,
      "disadvantage": -0.0559,
      "matches": 48106
    }
  ]
}